[{"type":"line text","chapterNumber":58,"verseNumber":21,"sectionNumber":1,"value":" "},{"type":"line text","chapterNumber":58,"verseNumber":1,"sectionNumber":1,"value":"“Cry aloud! Don’t spare! "},{"type":"line break"},{"type":"line text","chapterNumber":58,"verseNumber":1,"sectionNumber":2,"value":"Lift up your voice like a trumpet! "},{"type":"line break"},{"type":"line text","chapterNumber":58,"verseNumber":1,"sectionNumber":3,"value":"Declare to my people their disobedience, "},{"type":"line break"},{"type":"line text","chapterNumber":58,"verseNumber":1,"sectionNumber":4,"value":"and to the house of Jacob their sins. "},{"type":"line break"},{"type":"line text","chapterNumber":58,"verseNumber":2,"sectionNumber":1,"value":"Yet they seek me daily, "},{"type":"line break"},{"type":"line text","chapterNumber":58,"verseNumber":2,"sectionNumber":2,"value":"and delight to know my ways. "},{"type":"line break"},{"type":"line text","chapterNumber":58,"verseNumber":2,"sectionNumber":3,"value":"As a nation that did righteousness, "},{"type":"line break"},{"type":"line text","chapterNumber":58,"verseNumber":2,"sectionNumber":4,"value":"and didn’t forsake the ordinance of their God, "},{"type":"line break"},{"type":"line text","chapterNumber":58,"verseNumber":2,"sectionNumber":5,"value":"they ask of me righteous judgments. "},{"type":"line break"},{"type":"line text","chapterNumber":58,"verseNumber":2,"sectionNumber":6,"value":"They delight to draw near to God. "},{"type":"line break"},{"type":"line text","chapterNumber":58,"verseNumber":3,"sectionNumber":1,"value":"‘Why have we fasted,’ they say, ‘and you don’t see? "},{"type":"line break"},{"type":"line text","chapterNumber":58,"verseNumber":3,"sectionNumber":2,"value":"Why have we afflicted our soul, and you don’t notice?’ "},{"type":"line break"},{"type":"stanza end"},{"type":"stanza start"},{"type":"line text","chapterNumber":58,"verseNumber":3,"sectionNumber":3,"value":"“Behold, in the day of your fast you find pleasure, "},{"type":"line break"},{"type":"line text","chapterNumber":58,"verseNumber":3,"sectionNumber":4,"value":"and oppress all your laborers. "},{"type":"line break"},{"type":"line text","chapterNumber":58,"verseNumber":4,"sectionNumber":1,"value":"Behold, you fast for strife and contention, "},{"type":"line break"},{"type":"line text","chapterNumber":58,"verseNumber":4,"sectionNumber":2,"value":"and to strike with the fist of wickedness. "},{"type":"line break"},{"type":"line text","chapterNumber":58,"verseNumber":4,"sectionNumber":3,"value":"You don’t fast today so as to make your voice to be heard on high. "},{"type":"line break"},{"type":"line text","chapterNumber":58,"verseNumber":5,"sectionNumber":1,"value":"Is this the fast that I have chosen? "},{"type":"line break"},{"type":"line text","chapterNumber":58,"verseNumber":5,"sectionNumber":2,"value":"A day for a man to humble his soul? "},{"type":"line break"},{"type":"line text","chapterNumber":58,"verseNumber":5,"sectionNumber":3,"value":"Is it to bow down his head like a reed, "},{"type":"line break"},{"type":"line text","chapterNumber":58,"verseNumber":5,"sectionNumber":4,"value":"and to spread sackcloth and ashes under himself? "},{"type":"line break"},{"type":"line text","chapterNumber":58,"verseNumber":5,"sectionNumber":5,"value":"Will you call this a fast, "},{"type":"line break"},{"type":"line text","chapterNumber":58,"verseNumber":5,"sectionNumber":6,"value":"and an acceptable day to Yahweh? "},{"type":"line break"},{"type":"stanza end"},{"type":"stanza start"},{"type":"line text","chapterNumber":58,"verseNumber":5,"sectionNumber":7,"value":" "},{"type":"line text","chapterNumber":58,"verseNumber":6,"sectionNumber":1,"value":"“Isn’t this the fast that I have chosen: "},{"type":"line break"},{"type":"line text","chapterNumber":58,"verseNumber":6,"sectionNumber":2,"value":"to release the bonds of wickedness, "},{"type":"line break"},{"type":"line text","chapterNumber":58,"verseNumber":6,"sectionNumber":3,"value":"to undo the straps of the yoke, "},{"type":"line break"},{"type":"line text","chapterNumber":58,"verseNumber":6,"sectionNumber":4,"value":"to let the oppressed go free, "},{"type":"line break"},{"type":"line text","chapterNumber":58,"verseNumber":6,"sectionNumber":5,"value":"and that you break every yoke? "},{"type":"line break"},{"type":"line text","chapterNumber":58,"verseNumber":7,"sectionNumber":1,"value":"Isn’t it to distribute your bread to the hungry, "},{"type":"line break"},{"type":"line text","chapterNumber":58,"verseNumber":7,"sectionNumber":2,"value":"and that you bring the poor who are cast out to your house? "},{"type":"line break"},{"type":"line text","chapterNumber":58,"verseNumber":7,"sectionNumber":3,"value":"When you see the naked, "},{"type":"line break"},{"type":"line text","chapterNumber":58,"verseNumber":7,"sectionNumber":4,"value":"that you cover him; "},{"type":"line break"},{"type":"line text","chapterNumber":58,"verseNumber":7,"sectionNumber":5,"value":"and that you not hide yourself from your own flesh? "},{"type":"line break"},{"type":"line text","chapterNumber":58,"verseNumber":8,"sectionNumber":1,"value":"Then your light will break out as the morning, "},{"type":"line break"},{"type":"line text","chapterNumber":58,"verseNumber":8,"sectionNumber":2,"value":"and your healing will appear quickly; "},{"type":"line break"},{"type":"line text","chapterNumber":58,"verseNumber":8,"sectionNumber":3,"value":"then your righteousness shall go before you, "},{"type":"line break"},{"type":"line text","chapterNumber":58,"verseNumber":8,"sectionNumber":4,"value":"and Yahweh’s glory will be your rear guard. "},{"type":"line break"},{"type":"line text","chapterNumber":58,"verseNumber":9,"sectionNumber":1,"value":"Then you will call, and Yahweh will answer. "},{"type":"line break"},{"type":"line text","chapterNumber":58,"verseNumber":9,"sectionNumber":2,"value":"You will cry for help, and he will say, ‘Here I am.’ "},{"type":"line break"},{"type":"stanza end"},{"type":"stanza start"},{"type":"line text","chapterNumber":58,"verseNumber":9,"sectionNumber":3,"value":"“If you take away from among you the yoke, "},{"type":"line break"},{"type":"line text","chapterNumber":58,"verseNumber":9,"sectionNumber":4,"value":"finger pointing, "},{"type":"line break"},{"type":"line text","chapterNumber":58,"verseNumber":9,"sectionNumber":5,"value":"and speaking wickedly; "},{"type":"line break"},{"type":"line text","chapterNumber":58,"verseNumber":10,"sectionNumber":1,"value":"and if you pour out your soul to the hungry, "},{"type":"line break"},{"type":"line text","chapterNumber":58,"verseNumber":10,"sectionNumber":2,"value":"and satisfy the afflicted soul, "},{"type":"line break"},{"type":"line text","chapterNumber":58,"verseNumber":10,"sectionNumber":3,"value":"then your light will rise in darkness, "},{"type":"line break"},{"type":"line text","chapterNumber":58,"verseNumber":10,"sectionNumber":4,"value":"and your obscurity will be as the noonday; "},{"type":"line break"},{"type":"line text","chapterNumber":58,"verseNumber":11,"sectionNumber":1,"value":"and Yahweh will guide you continually, "},{"type":"line break"},{"type":"line text","chapterNumber":58,"verseNumber":11,"sectionNumber":2,"value":"satisfy your soul in dry places, "},{"type":"line break"},{"type":"line text","chapterNumber":58,"verseNumber":11,"sectionNumber":3,"value":"and make your bones strong. "},{"type":"line break"},{"type":"line text","chapterNumber":58,"verseNumber":11,"sectionNumber":4,"value":"You will be like a watered garden, "},{"type":"line break"},{"type":"line text","chapterNumber":58,"verseNumber":11,"sectionNumber":5,"value":"and like a spring of water "},{"type":"line break"},{"type":"line text","chapterNumber":58,"verseNumber":11,"sectionNumber":6,"value":"whose waters don’t fail. "},{"type":"line break"},{"type":"line text","chapterNumber":58,"verseNumber":12,"sectionNumber":1,"value":"Those who will be of you will build the old waste places. "},{"type":"line break"},{"type":"line text","chapterNumber":58,"verseNumber":12,"sectionNumber":2,"value":"You will raise up the foundations of many generations. "},{"type":"line break"},{"type":"line text","chapterNumber":58,"verseNumber":12,"sectionNumber":3,"value":"You will be called Repairer of the Breach, "},{"type":"line break"},{"type":"line text","chapterNumber":58,"verseNumber":12,"sectionNumber":4,"value":"Restorer of Paths with Dwellings. "},{"type":"line break"},{"type":"stanza end"},{"type":"stanza start"},{"type":"line text","chapterNumber":58,"verseNumber":12,"sectionNumber":5,"value":" "},{"type":"line text","chapterNumber":58,"verseNumber":13,"sectionNumber":1,"value":"“If you turn away your foot from the Sabbath, "},{"type":"line break"},{"type":"line text","chapterNumber":58,"verseNumber":13,"sectionNumber":2,"value":"from doing your pleasure on my holy day; "},{"type":"line break"},{"type":"line text","chapterNumber":58,"verseNumber":13,"sectionNumber":3,"value":"and call the Sabbath a delight, "},{"type":"line break"},{"type":"line text","chapterNumber":58,"verseNumber":13,"sectionNumber":4,"value":"and the holy of Yahweh honorable; "},{"type":"line break"},{"type":"line text","chapterNumber":58,"verseNumber":13,"sectionNumber":5,"value":"and honor it, "},{"type":"line break"},{"type":"line text","chapterNumber":58,"verseNumber":13,"sectionNumber":6,"value":"not doing your own ways, "},{"type":"line break"},{"type":"line text","chapterNumber":58,"verseNumber":13,"sectionNumber":7,"value":"nor finding your own pleasure, "},{"type":"line break"},{"type":"line text","chapterNumber":58,"verseNumber":13,"sectionNumber":8,"value":"nor speaking your own words, "},{"type":"line break"},{"type":"line text","chapterNumber":58,"verseNumber":14,"sectionNumber":1,"value":"then you will delight yourself in Yahweh, "},{"type":"line break"},{"type":"line text","chapterNumber":58,"verseNumber":14,"sectionNumber":2,"value":"and I will make you to ride on the high places of the earth, "},{"type":"line break"},{"type":"line text","chapterNumber":58,"verseNumber":14,"sectionNumber":3,"value":"and I will feed you with the heritage of Jacob your father;” "},{"type":"line break"},{"type":"line text","chapterNumber":58,"verseNumber":14,"sectionNumber":4,"value":"for Yahweh’s mouth has spoken it. "},{"type":"line break"}]