[{"type":"paragraph start"},{"type":"paragraph text","chapterNumber":1,"verseNumber":1,"sectionNumber":1,"value":"The vision of Isaiah the son of Amoz, which he saw concerning Judah and Jerusalem, in the days of Uzziah, Jotham, Ahaz, and Hezekiah, kings of Judah. "},{"type":"paragraph end"},{"type":"stanza start"},{"type":"line text","chapterNumber":1,"verseNumber":1,"sectionNumber":2,"value":" "},{"type":"line text","chapterNumber":1,"verseNumber":2,"sectionNumber":1,"value":"Hear, heavens, "},{"type":"line break"},{"type":"line text","chapterNumber":1,"verseNumber":2,"sectionNumber":2,"value":"and listen, earth; for Yahweh has spoken: "},{"type":"line break"},{"type":"line text","chapterNumber":1,"verseNumber":2,"sectionNumber":3,"value":"“I have nourished and brought up children "},{"type":"line break"},{"type":"line text","chapterNumber":1,"verseNumber":2,"sectionNumber":4,"value":"and they have rebelled against me. "},{"type":"line break"},{"type":"line text","chapterNumber":1,"verseNumber":3,"sectionNumber":1,"value":"The ox knows his owner, "},{"type":"line break"},{"type":"line text","chapterNumber":1,"verseNumber":3,"sectionNumber":2,"value":"and the donkey his master’s crib; "},{"type":"line break"},{"type":"line text","chapterNumber":1,"verseNumber":3,"sectionNumber":3,"value":"but Israel doesn’t know. "},{"type":"line break"},{"type":"line text","chapterNumber":1,"verseNumber":3,"sectionNumber":4,"value":"My people don’t consider.” "},{"type":"line break"},{"type":"line text","chapterNumber":1,"verseNumber":4,"sectionNumber":1,"value":"Ah sinful nation, "},{"type":"line break"},{"type":"line text","chapterNumber":1,"verseNumber":4,"sectionNumber":2,"value":"a people loaded with iniquity, "},{"type":"line break"},{"type":"line text","chapterNumber":1,"verseNumber":4,"sectionNumber":3,"value":"offspring of evildoers, "},{"type":"line break"},{"type":"line text","chapterNumber":1,"verseNumber":4,"sectionNumber":4,"value":"children who deal corruptly! "},{"type":"line break"},{"type":"line text","chapterNumber":1,"verseNumber":4,"sectionNumber":5,"value":"They have forsaken Yahweh. "},{"type":"line break"},{"type":"line text","chapterNumber":1,"verseNumber":4,"sectionNumber":6,"value":"They have despised the Holy One of Israel. "},{"type":"line break"},{"type":"line text","chapterNumber":1,"verseNumber":4,"sectionNumber":7,"value":"They are estranged and backward. "},{"type":"line break"},{"type":"line text","chapterNumber":1,"verseNumber":5,"sectionNumber":1,"value":"Why should you be beaten more, "},{"type":"line break"},{"type":"line text","chapterNumber":1,"verseNumber":5,"sectionNumber":2,"value":"that you revolt more and more? "},{"type":"line break"},{"type":"line text","chapterNumber":1,"verseNumber":5,"sectionNumber":3,"value":"The whole head is sick, "},{"type":"line break"},{"type":"line text","chapterNumber":1,"verseNumber":5,"sectionNumber":4,"value":"and the whole heart faint. "},{"type":"line break"},{"type":"line text","chapterNumber":1,"verseNumber":6,"sectionNumber":1,"value":"From the sole of the foot even to the head there is no soundness in it: "},{"type":"line break"},{"type":"line text","chapterNumber":1,"verseNumber":6,"sectionNumber":2,"value":"wounds, welts, and open sores. "},{"type":"line break"},{"type":"line text","chapterNumber":1,"verseNumber":6,"sectionNumber":3,"value":"They haven’t been closed, bandaged, or soothed with oil. "},{"type":"line break"},{"type":"line text","chapterNumber":1,"verseNumber":7,"sectionNumber":1,"value":"Your country is desolate. "},{"type":"line break"},{"type":"line text","chapterNumber":1,"verseNumber":7,"sectionNumber":2,"value":"Your cities are burned with fire. "},{"type":"line break"},{"type":"line text","chapterNumber":1,"verseNumber":7,"sectionNumber":3,"value":"Strangers devour your land in your presence "},{"type":"line break"},{"type":"line text","chapterNumber":1,"verseNumber":7,"sectionNumber":4,"value":"and it is desolate, "},{"type":"line break"},{"type":"line text","chapterNumber":1,"verseNumber":7,"sectionNumber":5,"value":"as overthrown by strangers. "},{"type":"line break"},{"type":"line text","chapterNumber":1,"verseNumber":8,"sectionNumber":1,"value":"The daughter of Zion is left like a shelter in a vineyard, "},{"type":"line break"},{"type":"line text","chapterNumber":1,"verseNumber":8,"sectionNumber":2,"value":"like a hut in a field of melons, "},{"type":"line break"},{"type":"line text","chapterNumber":1,"verseNumber":8,"sectionNumber":3,"value":"like a besieged city. "},{"type":"line break"},{"type":"line text","chapterNumber":1,"verseNumber":9,"sectionNumber":1,"value":"Unless Yahweh of Armies had left to us a very small remnant, "},{"type":"line break"},{"type":"line text","chapterNumber":1,"verseNumber":9,"sectionNumber":2,"value":"we would have been as Sodom. "},{"type":"line break"},{"type":"line text","chapterNumber":1,"verseNumber":9,"sectionNumber":3,"value":"We would have been like Gomorrah. "},{"type":"line break"},{"type":"stanza end"},{"type":"stanza start"},{"type":"line text","chapterNumber":1,"verseNumber":9,"sectionNumber":4,"value":" "},{"type":"line text","chapterNumber":1,"verseNumber":10,"sectionNumber":1,"value":"Hear Yahweh’s word, you rulers of Sodom! "},{"type":"line break"},{"type":"line text","chapterNumber":1,"verseNumber":10,"sectionNumber":2,"value":"Listen to the law of our God, you people of Gomorrah! "},{"type":"line break"},{"type":"line text","chapterNumber":1,"verseNumber":11,"sectionNumber":1,"value":"“What are the multitude of your sacrifices to me?”, says Yahweh. "},{"type":"line break"},{"type":"line text","chapterNumber":1,"verseNumber":11,"sectionNumber":2,"value":"“I have had enough of the burnt offerings of rams "},{"type":"line break"},{"type":"line text","chapterNumber":1,"verseNumber":11,"sectionNumber":3,"value":"and the fat of fed animals. "},{"type":"line break"},{"type":"line text","chapterNumber":1,"verseNumber":11,"sectionNumber":4,"value":"I don’t delight in the blood of bulls, "},{"type":"line break"},{"type":"line text","chapterNumber":1,"verseNumber":11,"sectionNumber":5,"value":"or of lambs, "},{"type":"line break"},{"type":"line text","chapterNumber":1,"verseNumber":11,"sectionNumber":6,"value":"or of male goats. "},{"type":"line break"},{"type":"line text","chapterNumber":1,"verseNumber":12,"sectionNumber":1,"value":"When you come to appear before me, "},{"type":"line break"},{"type":"line text","chapterNumber":1,"verseNumber":12,"sectionNumber":2,"value":"who has required this at your hand, to trample my courts? "},{"type":"line break"},{"type":"line text","chapterNumber":1,"verseNumber":13,"sectionNumber":1,"value":"Bring no more vain offerings. "},{"type":"line break"},{"type":"line text","chapterNumber":1,"verseNumber":13,"sectionNumber":2,"value":"Incense is an abomination to me. "},{"type":"line break"},{"type":"line text","chapterNumber":1,"verseNumber":13,"sectionNumber":3,"value":"New moons, Sabbaths, and convocations: "},{"type":"line break"},{"type":"line text","chapterNumber":1,"verseNumber":13,"sectionNumber":4,"value":"I can’t stand evil assemblies. "},{"type":"line break"},{"type":"line text","chapterNumber":1,"verseNumber":14,"sectionNumber":1,"value":"My soul hates your New Moons and your appointed feasts. "},{"type":"line break"},{"type":"line text","chapterNumber":1,"verseNumber":14,"sectionNumber":2,"value":"They are a burden to me. "},{"type":"line break"},{"type":"line text","chapterNumber":1,"verseNumber":14,"sectionNumber":3,"value":"I am weary of bearing them. "},{"type":"line break"},{"type":"line text","chapterNumber":1,"verseNumber":15,"sectionNumber":1,"value":"When you spread out your hands, I will hide my eyes from you. "},{"type":"line break"},{"type":"line text","chapterNumber":1,"verseNumber":15,"sectionNumber":2,"value":"Yes, when you make many prayers, I will not hear. "},{"type":"line break"},{"type":"line text","chapterNumber":1,"verseNumber":15,"sectionNumber":3,"value":"Your hands are full of blood. "},{"type":"line break"},{"type":"line text","chapterNumber":1,"verseNumber":16,"sectionNumber":1,"value":"Wash yourselves. Make yourself clean. "},{"type":"line break"},{"type":"line text","chapterNumber":1,"verseNumber":16,"sectionNumber":2,"value":"Put away the evil of your doings from before my eyes. "},{"type":"line break"},{"type":"line text","chapterNumber":1,"verseNumber":16,"sectionNumber":3,"value":"Cease to do evil. "},{"type":"line break"},{"type":"line text","chapterNumber":1,"verseNumber":17,"sectionNumber":1,"value":"Learn to do well. "},{"type":"line break"},{"type":"line text","chapterNumber":1,"verseNumber":17,"sectionNumber":2,"value":"Seek justice. "},{"type":"line break"},{"type":"line text","chapterNumber":1,"verseNumber":17,"sectionNumber":3,"value":"Relieve the oppressed. "},{"type":"line break"},{"type":"line text","chapterNumber":1,"verseNumber":17,"sectionNumber":4,"value":"Defend the fatherless. "},{"type":"line break"},{"type":"line text","chapterNumber":1,"verseNumber":17,"sectionNumber":5,"value":"Plead for the widow.” "},{"type":"line break"},{"type":"stanza end"},{"type":"stanza start"},{"type":"line text","chapterNumber":1,"verseNumber":17,"sectionNumber":6,"value":" "},{"type":"line text","chapterNumber":1,"verseNumber":18,"sectionNumber":1,"value":"“Come now, and let’s reason together,” says Yahweh: "},{"type":"line break"},{"type":"line text","chapterNumber":1,"verseNumber":18,"sectionNumber":2,"value":"“Though your sins are as scarlet, they shall be as white as snow. "},{"type":"line break"},{"type":"line text","chapterNumber":1,"verseNumber":18,"sectionNumber":3,"value":"Though they are red like crimson, they shall be as wool. "},{"type":"line break"},{"type":"line text","chapterNumber":1,"verseNumber":19,"sectionNumber":1,"value":"If you are willing and obedient, "},{"type":"line break"},{"type":"line text","chapterNumber":1,"verseNumber":19,"sectionNumber":2,"value":"you will eat the good of the land; "},{"type":"line break"},{"type":"line text","chapterNumber":1,"verseNumber":20,"sectionNumber":1,"value":"but if you refuse and rebel, you will be devoured with the sword; "},{"type":"line break"},{"type":"line text","chapterNumber":1,"verseNumber":20,"sectionNumber":2,"value":"for the mouth of Yahweh has spoken it.” "},{"type":"line break"},{"type":"stanza end"},{"type":"stanza start"},{"type":"line text","chapterNumber":1,"verseNumber":20,"sectionNumber":3,"value":" "},{"type":"line text","chapterNumber":1,"verseNumber":21,"sectionNumber":1,"value":"How the faithful city has become a prostitute! "},{"type":"line break"},{"type":"line text","chapterNumber":1,"verseNumber":21,"sectionNumber":2,"value":"She was full of justice. "},{"type":"line break"},{"type":"line text","chapterNumber":1,"verseNumber":21,"sectionNumber":3,"value":"Righteousness lodged in her, "},{"type":"line break"},{"type":"line text","chapterNumber":1,"verseNumber":21,"sectionNumber":4,"value":"but now there are murderers. "},{"type":"line break"},{"type":"line text","chapterNumber":1,"verseNumber":22,"sectionNumber":1,"value":"Your silver has become dross, "},{"type":"line break"},{"type":"line text","chapterNumber":1,"verseNumber":22,"sectionNumber":2,"value":"your wine mixed with water. "},{"type":"line break"},{"type":"line text","chapterNumber":1,"verseNumber":23,"sectionNumber":1,"value":"Your princes are rebellious and companions of thieves. "},{"type":"line break"},{"type":"line text","chapterNumber":1,"verseNumber":23,"sectionNumber":2,"value":"Everyone loves bribes and follows after rewards. "},{"type":"line break"},{"type":"line text","chapterNumber":1,"verseNumber":23,"sectionNumber":3,"value":"They don’t defend the fatherless, "},{"type":"line break"},{"type":"line text","chapterNumber":1,"verseNumber":23,"sectionNumber":4,"value":"neither does the cause of the widow come to them. "},{"type":"line break"},{"type":"stanza end"},{"type":"stanza start"},{"type":"line text","chapterNumber":1,"verseNumber":23,"sectionNumber":5,"value":" "},{"type":"line text","chapterNumber":1,"verseNumber":24,"sectionNumber":1,"value":"Therefore the Lord, Yahweh of Armies, "},{"type":"line break"},{"type":"line text","chapterNumber":1,"verseNumber":24,"sectionNumber":2,"value":"the Mighty One of Israel, says: "},{"type":"line break"},{"type":"line text","chapterNumber":1,"verseNumber":24,"sectionNumber":3,"value":"“Ah, I will get relief from my adversaries, "},{"type":"line break"},{"type":"line text","chapterNumber":1,"verseNumber":24,"sectionNumber":4,"value":"and avenge myself on my enemies. "},{"type":"line break"},{"type":"line text","chapterNumber":1,"verseNumber":25,"sectionNumber":1,"value":"I will turn my hand on you, "},{"type":"line break"},{"type":"line text","chapterNumber":1,"verseNumber":25,"sectionNumber":2,"value":"thoroughly purge away your dross, "},{"type":"line break"},{"type":"line text","chapterNumber":1,"verseNumber":25,"sectionNumber":3,"value":"and will take away all your tin. "},{"type":"line break"},{"type":"line text","chapterNumber":1,"verseNumber":26,"sectionNumber":1,"value":"I will restore your judges as at the first, "},{"type":"line break"},{"type":"line text","chapterNumber":1,"verseNumber":26,"sectionNumber":2,"value":"and your counselors as at the beginning. "},{"type":"line break"},{"type":"line text","chapterNumber":1,"verseNumber":26,"sectionNumber":3,"value":"Afterward you shall be called ‘The city of righteousness, "},{"type":"line break"},{"type":"line text","chapterNumber":1,"verseNumber":26,"sectionNumber":4,"value":"a faithful town.’ "},{"type":"line break"},{"type":"line text","chapterNumber":1,"verseNumber":27,"sectionNumber":1,"value":"Zion shall be redeemed with justice, "},{"type":"line break"},{"type":"line text","chapterNumber":1,"verseNumber":27,"sectionNumber":2,"value":"and her converts with righteousness. "},{"type":"line break"},{"type":"line text","chapterNumber":1,"verseNumber":28,"sectionNumber":1,"value":"But the destruction of transgressors and sinners shall be together, "},{"type":"line break"},{"type":"line text","chapterNumber":1,"verseNumber":28,"sectionNumber":2,"value":"and those who forsake Yahweh shall be consumed. "},{"type":"line break"},{"type":"line text","chapterNumber":1,"verseNumber":29,"sectionNumber":1,"value":"For they shall be ashamed of the oaks which you have desired, "},{"type":"line break"},{"type":"line text","chapterNumber":1,"verseNumber":29,"sectionNumber":2,"value":"and you shall be confounded for the gardens that you have chosen. "},{"type":"line break"},{"type":"line text","chapterNumber":1,"verseNumber":30,"sectionNumber":1,"value":"For you shall be as an oak whose leaf fades, "},{"type":"line break"},{"type":"line text","chapterNumber":1,"verseNumber":30,"sectionNumber":2,"value":"and as a garden that has no water. "},{"type":"line break"},{"type":"line text","chapterNumber":1,"verseNumber":31,"sectionNumber":1,"value":"The strong will be like tinder, "},{"type":"line break"},{"type":"line text","chapterNumber":1,"verseNumber":31,"sectionNumber":2,"value":"and his work like a spark. "},{"type":"line break"},{"type":"line text","chapterNumber":1,"verseNumber":31,"sectionNumber":3,"value":"They will both burn together, "},{"type":"line break"},{"type":"line text","chapterNumber":1,"verseNumber":31,"sectionNumber":4,"value":"and no one will quench them.” "},{"type":"line break"},{"type":"stanza end"},{"type":"paragraph start"}]